missing/__init__.py
missing/missing.py
handle_missing_csv-0.0.1.dist-info/LICENSE
handle_missing_csv-0.0.1.dist-info/METADATA
handle_missing_csv-0.0.1.dist-info/WHEEL
handle_missing_csv-0.0.1.dist-info/top_level.txt
handle_missing_csv-0.0.1.dist-info/RECORD
