Metadata-Version: 2.1
Name: handle-missing-csv
Version: 0.0.1
Summary: Handle both categorical and non-categorical missing values
Home-page: https://github.com/NoOne03/handle_missing_value.git
Author: Prateek Kr Singh
Author-email: prateekkumarsingh3@gmail.com
License: UNKNOWN
Platform: UNKNOWN
Classifier: Programming Language :: Python :: 3
Classifier: License :: OSI Approved :: MIT License
Classifier: Operating System :: OS Independent
Requires-Python: >=3.6
